jackfruit/__init__.py
jackfruit/_version.py
jackfruit/generic/__init__.py
jackfruit/generic/generic.py
jackfruit/generic/input.py
jackfruit/generic/menu.py
tests/__init__.py
tests/conftest.py
tests/test_generic.py
tests/test_generic_data.py
tests/test_generic_data_input.py
tests/test_generic_menu.py
tests/test_generic_text.py
tests/test_jackfruit.py
jackfruit-0.12.dist-info/LICENSE
jackfruit-0.12.dist-info/METADATA
jackfruit-0.12.dist-info/WHEEL
jackfruit-0.12.dist-info/top_level.txt
jackfruit-0.12.dist-info/RECORD
